chase/__init__.py
chase/account.py
chase/order.py
chase/session.py
chase/symbols.py
chase/urls.py
chaseAPI233-0.2.dist-info/LICENSE
chaseAPI233-0.2.dist-info/METADATA
chaseAPI233-0.2.dist-info/WHEEL
chaseAPI233-0.2.dist-info/top_level.txt
chaseAPI233-0.2.dist-info/RECORD
