Metadata-Version: 2.1
Name: chaseAPI233
Version: 0.2
Summary: An unofficial API for Chase Invest
Home-page: https://github.com/Jinzeld/chaseAPI233
Author: Jinzeld
Author-email: jinzeld@pm.me
License: MIT
Download-URL: https://github.com/Jinzeld/chaseAPI233/archive/refs/heads/main.zip
Keywords: CHASE,API
Platform: UNKNOWN
Classifier: Development Status :: 3 - Alpha
Classifier: Intended Audience :: Developers
Classifier: Topic :: Internet :: WWW/HTTP :: Session
Classifier: License :: OSI Approved :: MIT License
Classifier: Programming Language :: Python :: 3
Classifier: Programming Language :: Python :: 3.8
Classifier: Programming Language :: Python :: 3.9
Classifier: Programming Language :: Python :: 3.10
Classifier: Programming Language :: Python :: 3.11
License-File: LICENSE
Requires-Dist: playwright
Requires-Dist: playwright-stealth
